{
  "data": "20.03.2026",
  "generatedAt": "20.03.2026 08:02:32",
  "timezone": "Europe/Bucharest (EET)",
  "totalVerificari": 17,
  "minutVerificare": 53,
  "verificari": [
    {
      "matchId": "8n538fjB",
      "homeTeam": "Sp. Subotica",
      "awayTeam": "Radnik",
      "liga": "SERBIA: Mozzart Bet Super Liga",
      "oraStart": "18:00",
      "timestampStart": 1774022400,
      "oraVerificare": "18:53",
      "timestampVerificare": 1774025580,
      "minutMeci": 53,
      "status": "completat",
      "completedAt": "2026-03-20T16:52:39.304Z",
      "statsFile": "stats-8n538fjB-HT.json"
    },
    {
      "matchId": "AgTMuLWh",
      "homeTeam": "FCSB",
      "awayTeam": "UTA Arad",
      "liga": "ROMANIA: Superliga - Relegation Group",
      "oraStart": "19:00",
      "timestampStart": 1774026000,
      "oraVerificare": "19:51",
      "timestampVerificare": 1774029060,
      "minutMeci": 51,
      "status": "completat",
      "staggerOffset": -2,
      "completedAt": "2026-03-20T17:50:47.092Z",
      "statsFile": "stats-AgTMuLWh-HT.json"
    },
    {
      "matchId": "OA3wFr8j",
      "homeTeam": "Piast Gliwice",
      "awayTeam": "Radomiak Radom",
      "liga": "POLAND: Ekstraklasa",
      "oraStart": "19:00",
      "timestampStart": 1774026000,
      "oraVerificare": "19:53",
      "timestampVerificare": 1774029180,
      "minutMeci": 53,
      "status": "completat",
      "completedAt": "2026-03-20T17:52:34.247Z",
      "statsFile": "stats-OA3wFr8j-HT.json"
    },
    {
      "matchId": "pboX3CxB",
      "homeTeam": "Karlsruher SC",
      "awayTeam": "Greuther Furth",
      "liga": "GERMANY: 2. Bundesliga",
      "oraStart": "19:30",
      "timestampStart": 1774027800,
      "oraVerificare": "20:21",
      "timestampVerificare": 1774030860,
      "minutMeci": 51,
      "status": "completat",
      "staggerOffset": -2,
      "completedAt": "2026-03-20T18:20:34.552Z",
      "statsFile": "stats-pboX3CxB-HT.json"
    },
    {
      "matchId": "xbLAJJeK",
      "homeTeam": "Cagliari",
      "awayTeam": "Napoli",
      "liga": "ITALY: Serie A",
      "oraStart": "19:30",
      "timestampStart": 1774027800,
      "oraVerificare": "20:22",
      "timestampVerificare": 1774030920,
      "minutMeci": 52,
      "status": "completat",
      "staggerOffset": -1,
      "completedAt": "2026-03-20T18:21:34.516Z",
      "statsFile": "stats-xbLAJJeK-HT.json"
    },
    {
      "matchId": "hOlu2j7N",
      "homeTeam": "Hannover",
      "awayTeam": "Braunschweig",
      "liga": "GERMANY: 2. Bundesliga",
      "oraStart": "19:30",
      "timestampStart": 1774027800,
      "oraVerificare": "20:23",
      "timestampVerificare": 1774030980,
      "minutMeci": 53,
      "status": "completat",
      "completedAt": "2026-03-20T18:22:34.577Z",
      "statsFile": "stats-hOlu2j7N-HT.json"
    },
    {
      "matchId": "pWqJfXE5",
      "homeTeam": "Vejle",
      "awayTeam": "Odense",
      "liga": "DENMARK: Superliga - Relegation Group",
      "oraStart": "20:00",
      "timestampStart": 1774029600,
      "oraVerificare": "20:53",
      "timestampVerificare": 1774032780,
      "minutMeci": 53,
      "status": "completat",
      "completedAt": "2026-03-20T18:52:35.176Z",
      "statsFile": "stats-pWqJfXE5-HT.json"
    },
    {
      "matchId": "KQ3sNxE5",
      "homeTeam": "Sturm Graz",
      "awayTeam": "Salzburg",
      "liga": "AUSTRIA: Bundesliga - Championship Group",
      "oraStart": "20:30",
      "timestampStart": 1774031400,
      "oraVerificare": "21:23",
      "timestampVerificare": 1774034580,
      "minutMeci": 53,
      "status": "completat",
      "completedAt": "2026-03-20T19:22:35.739Z",
      "statsFile": "stats-KQ3sNxE5-HT.json"
    },
    {
      "matchId": "bXwzRakL",
      "homeTeam": "Heracles",
      "awayTeam": "Excelsior",
      "liga": "NETHERLANDS: Eredivisie",
      "oraStart": "21:00",
      "timestampStart": 1774033200,
      "oraVerificare": "21:53",
      "timestampVerificare": 1774036380,
      "minutMeci": 53,
      "status": "completat",
      "completedAt": "2026-03-20T19:52:36.259Z",
      "statsFile": "stats-bXwzRakL-HT.json"
    },
    {
      "matchId": "rwDrQ8Gi",
      "homeTeam": "Motor Lublin",
      "awayTeam": "Zaglebie",
      "liga": "POLAND: Ekstraklasa",
      "oraStart": "21:30",
      "timestampStart": 1774035000,
      "oraVerificare": "22:21",
      "timestampVerificare": 1774038060,
      "minutMeci": 51,
      "status": "completat",
      "staggerOffset": -2,
      "completedAt": "2026-03-20T20:20:36.811Z",
      "statsFile": "stats-rwDrQ8Gi-HT.json"
    },
    {
      "matchId": "SrS8qyAO",
      "homeTeam": "RB Leipzig",
      "awayTeam": "Hoffenheim",
      "liga": "GERMANY: Bundesliga",
      "oraStart": "21:30",
      "timestampStart": 1774035000,
      "oraVerificare": "22:23",
      "timestampVerificare": 1774038180,
      "minutMeci": 53,
      "status": "completat",
      "completedAt": "2026-03-20T20:22:57.790Z",
      "statsFile": "stats-SrS8qyAO-HT.json"
    },
    {
      "matchId": "zg3cAFI6",
      "homeTeam": "Genoa",
      "awayTeam": "Udinese",
      "liga": "ITALY: Serie A",
      "oraStart": "21:45",
      "timestampStart": 1774035900,
      "oraVerificare": "22:36",
      "timestampVerificare": 1774038960,
      "minutMeci": 51,
      "status": "completat",
      "staggerOffset": -2,
      "completedAt": "2026-03-20T20:35:52.149Z",
      "statsFile": "stats-zg3cAFI6-HT.json"
    },
    {
      "matchId": "vgQi3gRP",
      "homeTeam": "Lens",
      "awayTeam": "Angers",
      "liga": "FRANCE: Ligue 1",
      "oraStart": "21:45",
      "timestampStart": 1774035900,
      "oraVerificare": "22:38",
      "timestampVerificare": 1774039080,
      "minutMeci": 53,
      "status": "completat",
      "completedAt": "2026-03-20T20:38:03.484Z",
      "statsFile": "stats-vgQi3gRP-HT.json"
    },
    {
      "matchId": "xnX3PJ6T",
      "homeTeam": "Preston",
      "awayTeam": "Stoke",
      "liga": "ENGLAND: Championship",
      "oraStart": "22:00",
      "timestampStart": 1774036800,
      "oraVerificare": "22:51",
      "timestampVerificare": 1774039860,
      "minutMeci": 51,
      "status": "completat",
      "staggerOffset": -2,
      "completedAt": "2026-03-20T20:50:57.580Z",
      "statsFile": "stats-xnX3PJ6T-HT.json"
    },
    {
      "matchId": "pIFbK5HM",
      "homeTeam": "Villarreal",
      "awayTeam": "Real Sociedad",
      "liga": "SPAIN: LaLiga",
      "oraStart": "22:00",
      "timestampStart": 1774036800,
      "oraVerificare": "22:52",
      "timestampVerificare": 1774039920,
      "minutMeci": 52,
      "status": "completat",
      "staggerOffset": -1,
      "completedAt": "2026-03-20T20:52:04.323Z",
      "statsFile": "stats-pIFbK5HM-HT.json"
    },
    {
      "matchId": "QZ5U62OH",
      "homeTeam": "Bournemouth",
      "awayTeam": "Manchester Utd",
      "liga": "ENGLAND: Premier League",
      "oraStart": "22:00",
      "timestampStart": 1774036800,
      "oraVerificare": "22:53",
      "timestampVerificare": 1774039980,
      "minutMeci": 53,
      "status": "completat",
      "completedAt": "2026-03-20T20:53:02.518Z",
      "statsFile": "stats-QZ5U62OH-HT.json"
    },
    {
      "matchId": "2ughgZIU",
      "homeTeam": "Estrela",
      "awayTeam": "Casa Pia",
      "liga": "PORTUGAL: Liga Portugal",
      "oraStart": "22:15",
      "timestampStart": 1774037700,
      "oraVerificare": "23:08",
      "timestampVerificare": 1774040880,
      "minutMeci": 53,
      "status": "completat",
      "completedAt": "2026-03-20T21:07:11.804Z",
      "statsFile": "stats-2ughgZIU-HT.json"
    }
  ]
}