{
  "data": "29.11.2025",
  "generatedAt": "29.11.2025 08:00:05",
  "timezone": "Europe/Bucharest (EET)",
  "totalVerificari": 75,
  "minutVerificare": 45,
  "verificari": [
    {
      "matchId": "UybSXeMh",
      "homeTeam": "Rizespor",
      "awayTeam": "Kayserispor",
      "liga": "TURKEY: Super Lig",
      "oraStart": "13:30",
      "timestampStart": 1764415800,
      "oraVerificare": "14:15",
      "timestampVerificare": 1764418500,
      "minutMeci": 45,
      "status": "completat",
      "completedAt": "2025-11-29T12:14:29.591Z",
      "statsFile": "stats-UybSXeMh-HT.json"
    },
    {
      "matchId": "2asSpOqH",
      "homeTeam": "Braunschweig",
      "awayTeam": "Kaiserslautern",
      "liga": "GERMANY: 2. Bundesliga",
      "oraStart": "14:00",
      "timestampStart": 1764417600,
      "oraVerificare": "14:45",
      "timestampVerificare": 1764420300,
      "minutMeci": 45,
      "status": "completat",
      "completedAt": "2025-11-29T12:44:27.182Z",
      "statsFile": "stats-2asSpOqH-HT.json"
    },
    {
      "matchId": "0zoBl6ph",
      "homeTeam": "Greuther Furth",
      "awayTeam": "Bochum",
      "liga": "GERMANY: 2. Bundesliga",
      "oraStart": "14:00",
      "timestampStart": 1764417600,
      "oraVerificare": "14:45",
      "timestampVerificare": 1764420300,
      "minutMeci": 45,
      "status": "completat",
      "completedAt": "2025-11-29T12:44:29.077Z",
      "statsFile": "stats-0zoBl6ph-HT.json"
    },
    {
      "matchId": "l2Gsi1Sg",
      "homeTeam": "Ilioupoli",
      "awayTeam": "Kalamata",
      "liga": "GREECE: Super League 2",
      "oraStart": "14:00",
      "timestampStart": 1764417600,
      "oraVerificare": "14:45",
      "timestampVerificare": 1764420300,
      "minutMeci": 45,
      "status": "completat",
      "completedAt": "2025-11-29T12:44:29.565Z",
      "statsFile": "stats-l2Gsi1Sg-HT.json"
    },
    {
      "matchId": "Uo1f9L5m",
      "homeTeam": "Zeleznicar Pancevo",
      "awayTeam": "Radnicki 1923",
      "liga": "SERBIA: Mozzart Bet Super Liga",
      "oraStart": "14:00",
      "timestampStart": 1764417600,
      "oraVerificare": "14:45",
      "timestampVerificare": 1764420300,
      "minutMeci": 45,
      "status": "completat",
      "completedAt": "2025-11-29T12:44:37.344Z",
      "statsFile": "stats-Uo1f9L5m-HT.json"
    },
    {
      "matchId": "YgILiMYp",
      "homeTeam": "Leicester",
      "awayTeam": "Sheffield Utd",
      "liga": "ENGLAND: Championship",
      "oraStart": "14:30",
      "timestampStart": 1764419400,
      "oraVerificare": "15:15",
      "timestampVerificare": 1764422100,
      "minutMeci": 45,
      "status": "completat",
      "completedAt": "2025-11-29T13:14:27.574Z",
      "statsFile": "stats-YgILiMYp-HT.json"
    },
    {
      "matchId": "fNo34aIj",
      "homeTeam": "Portsmouth",
      "awayTeam": "Bristol City",
      "liga": "ENGLAND: Championship",
      "oraStart": "14:30",
      "timestampStart": 1764419400,
      "oraVerificare": "15:15",
      "timestampVerificare": 1764422100,
      "minutMeci": 45,
      "status": "completat",
      "completedAt": "2025-11-29T13:14:27.975Z",
      "statsFile": "stats-fNo34aIj-HT.json"
    },
    {
      "matchId": "IeXcQtuA",
      "homeTeam": "Stoke",
      "awayTeam": "Hull",
      "liga": "ENGLAND: Championship",
      "oraStart": "14:30",
      "timestampStart": 1764419400,
      "oraVerificare": "15:15",
      "timestampVerificare": 1764422100,
      "minutMeci": 45,
      "status": "completat",
      "completedAt": "2025-11-29T13:14:34.585Z",
      "statsFile": "stats-IeXcQtuA-HT.json"
    },
    {
      "matchId": "Is8bmJRI",
      "homeTeam": "Kavala",
      "awayTeam": "Chrisoupolis",
      "liga": "GREECE: Super League 2",
      "oraStart": "15:00",
      "timestampStart": 1764421200,
      "oraVerificare": "15:45",
      "timestampVerificare": 1764423900,
      "minutMeci": 45,
      "status": "completat",
      "completedAt": "2025-11-29T13:44:35.218Z",
      "statsFile": "stats-Is8bmJRI-HT.json"
    },
    {
      "matchId": "d4y3bqzK",
      "homeTeam": "Marko",
      "awayTeam": "PAE Egaleo",
      "liga": "GREECE: Super League 2",
      "oraStart": "15:00",
      "timestampStart": 1764421200,
      "oraVerificare": "15:45",
      "timestampVerificare": 1764423900,
      "minutMeci": 45,
      "status": "completat",
      "completedAt": "2025-11-29T13:44:37.209Z",
      "statsFile": "stats-d4y3bqzK-HT.json"
    },
    {
      "matchId": "4OeJ3HZO",
      "homeTeam": "Mladost",
      "awayTeam": "Radnicki Nis",
      "liga": "SERBIA: Mozzart Bet Super Liga",
      "oraStart": "15:00",
      "timestampStart": 1764421200,
      "oraVerificare": "15:45",
      "timestampVerificare": 1764423900,
      "minutMeci": 45,
      "status": "completat",
      "completedAt": "2025-11-29T13:44:37.624Z",
      "statsFile": "stats-4OeJ3HZO-HT.json"
    },
    {
      "matchId": "CtiBYirA",
      "homeTeam": "Mallorca",
      "awayTeam": "Osasuna",
      "liga": "SPAIN: LaLiga",
      "oraStart": "15:00",
      "timestampStart": 1764421200,
      "oraVerificare": "15:45",
      "timestampVerificare": 1764423900,
      "minutMeci": 45,
      "status": "completat",
      "completedAt": "2025-11-29T13:44:41.986Z",
      "statsFile": "stats-CtiBYirA-HT.json"
    },
    {
      "matchId": "YLIhr7XH",
      "homeTeam": "Ceuta",
      "awayTeam": "Burgos CF",
      "liga": "SPAIN: LaLiga2",
      "oraStart": "15:00",
      "timestampStart": 1764421200,
      "oraVerificare": "15:45",
      "timestampVerificare": 1764423900,
      "minutMeci": 45,
      "status": "completat",
      "completedAt": "2025-11-29T13:44:42.439Z",
      "statsFile": "stats-YLIhr7XH-HT.json"
    },
    {
      "matchId": "67fpbQJD",
      "homeTeam": "Genoa",
      "awayTeam": "Verona",
      "liga": "ITALY: Serie A",
      "oraStart": "16:00",
      "timestampStart": 1764424800,
      "oraVerificare": "16:45",
      "timestampVerificare": 1764427500,
      "minutMeci": 45,
      "status": "completat",
      "completedAt": "2025-11-29T14:44:29.219Z",
      "statsFile": "stats-67fpbQJD-HT.json"
    },
    {
      "matchId": "nR1HdYa6",
      "homeTeam": "Parma",
      "awayTeam": "Udinese",
      "liga": "ITALY: Serie A",
      "oraStart": "16:00",
      "timestampStart": 1764424800,
      "oraVerificare": "16:45",
      "timestampVerificare": 1764427500,
      "minutMeci": 45,
      "status": "completat",
      "completedAt": "2025-11-29T14:44:35.679Z",
      "statsFile": "stats-nR1HdYa6-HT.json"
    },
    {
      "matchId": "EFbDSy4S",
      "homeTeam": "Norrkoping",
      "awayTeam": "Orgryte",
      "liga": "SWEDEN: Allsvenskan - Relegation",
      "oraStart": "16:00",
      "timestampStart": 1764424800,
      "oraVerificare": "16:45",
      "timestampVerificare": 1764427500,
      "minutMeci": 45,
      "status": "completat",
      "completedAt": "2025-11-29T14:44:48.524Z",
      "statsFile": "stats-EFbDSy4S-HT.json"
    },
    {
      "matchId": "GUsCV5uP",
      "homeTeam": "Gaziantep",
      "awayTeam": "Eyupspor",
      "liga": "TURKEY: Super Lig",
      "oraStart": "16:00",
      "timestampStart": 1764424800,
      "oraVerificare": "16:45",
      "timestampVerificare": 1764427500,
      "minutMeci": 45,
      "status": "completat",
      "completedAt": "2025-11-29T14:44:55.351Z",
      "statsFile": "stats-GUsCV5uP-HT.json"
    },
    {
      "matchId": "pzVmwjfL",
      "homeTeam": "Bayern Munich",
      "awayTeam": "St. Pauli",
      "liga": "GERMANY: Bundesliga",
      "oraStart": "16:30",
      "timestampStart": 1764426600,
      "oraVerificare": "17:15",
      "timestampVerificare": 1764429300,
      "minutMeci": 45,
      "status": "completat",
      "completedAt": "2025-11-29T15:14:36.329Z",
      "statsFile": "stats-pzVmwjfL-HT.json"
    },
    {
      "matchId": "O2m9roW0",
      "homeTeam": "Hoffenheim",
      "awayTeam": "Augsburg",
      "liga": "GERMANY: Bundesliga",
      "oraStart": "16:30",
      "timestampStart": 1764426600,
      "oraVerificare": "17:15",
      "timestampVerificare": 1764429300,
      "minutMeci": 45,
      "status": "completat",
      "completedAt": "2025-11-29T15:14:36.789Z",
      "statsFile": "stats-O2m9roW0-HT.json"
    },
    {
      "matchId": "WnyzsZJF",
      "homeTeam": "FC Arges",
      "awayTeam": "CFR Cluj",
      "liga": "ROMANIA: Superliga",
      "oraStart": "16:30",
      "timestampStart": 1764426600,
      "oraVerificare": "17:15",
      "timestampVerificare": 1764429300,
      "minutMeci": 45,
      "status": "completat",
      "completedAt": "2025-11-29T15:14:41.332Z",
      "statsFile": "stats-WnyzsZJF-HT.json"
    },
    {
      "matchId": "Q1AzuSTk",
      "homeTeam": "Dender",
      "awayTeam": "Westerlo",
      "liga": "BELGIUM: Jupiler Pro League",
      "oraStart": "17:00",
      "timestampStart": 1764428400,
      "oraVerificare": "17:45",
      "timestampVerificare": 1764431100,
      "minutMeci": 45,
      "status": "completat",
      "completedAt": "2025-11-29T15:44:31.515Z",
      "statsFile": "stats-Q1AzuSTk-HT.json"
    },
    {
      "matchId": "EVdIoFG5",
      "homeTeam": "Sporting Lokeren",
      "awayTeam": "Kortrijk",
      "liga": "BELGIUM: Challenger Pro League",
      "oraStart": "17:00",
      "timestampStart": 1764428400,
      "oraVerificare": "17:45",
      "timestampVerificare": 1764431100,
      "minutMeci": 45,
      "status": "completat",
      "completedAt": "2025-11-29T15:44:37.481Z",
      "statsFile": "stats-EVdIoFG5-HT.json"
    },
    {
      "matchId": "MLedjISG",
      "homeTeam": "Brentford",
      "awayTeam": "Burnley",
      "liga": "ENGLAND: Premier League",
      "oraStart": "17:00",
      "timestampStart": 1764428400,
      "oraVerificare": "17:45",
      "timestampVerificare": 1764431100,
      "minutMeci": 45,
      "status": "completat",
      "completedAt": "2025-11-29T15:44:42.515Z",
      "statsFile": "stats-MLedjISG-HT.json"
    },
    {
      "matchId": "nwbN4HsA",
      "homeTeam": "Manchester City",
      "awayTeam": "Leeds",
      "liga": "ENGLAND: Premier League",
      "oraStart": "17:00",
      "timestampStart": 1764428400,
      "oraVerificare": "17:45",
      "timestampVerificare": 1764431100,
      "minutMeci": 45,
      "status": "completat",
      "completedAt": "2025-11-29T15:44:43.024Z",
      "statsFile": "stats-nwbN4HsA-HT.json"
    },
    {
      "matchId": "vyw2cZZq",
      "homeTeam": "Sunderland",
      "awayTeam": "Bournemouth",
      "liga": "ENGLAND: Premier League",
      "oraStart": "17:00",
      "timestampStart": 1764428400,
      "oraVerificare": "17:45",
      "timestampVerificare": 1764431100,
      "minutMeci": 45,
      "status": "completat",
      "completedAt": "2025-11-29T15:44:45.107Z",
      "statsFile": "stats-vyw2cZZq-HT.json"
    },
    {
      "matchId": "OKWkcrBN",
      "homeTeam": "Coventry",
      "awayTeam": "Charlton",
      "liga": "ENGLAND: Championship",
      "oraStart": "17:00",
      "timestampStart": 1764428400,
      "oraVerificare": "17:45",
      "timestampVerificare": 1764431100,
      "minutMeci": 45,
      "status": "completat",
      "completedAt": "2025-11-29T15:44:46.968Z",
      "statsFile": "stats-OKWkcrBN-HT.json"
    },
    {
      "matchId": "l208FPQi",
      "homeTeam": "Middlesbrough",
      "awayTeam": "Derby",
      "liga": "ENGLAND: Championship",
      "oraStart": "17:00",
      "timestampStart": 1764428400,
      "oraVerificare": "17:45",
      "timestampVerificare": 1764431100,
      "minutMeci": 45,
      "status": "completat",
      "completedAt": "2025-11-29T15:44:53.492Z",
      "statsFile": "stats-l208FPQi-HT.json"
    },
    {
      "matchId": "MFbGD3e4",
      "homeTeam": "Millwall",
      "awayTeam": "Southampton",
      "liga": "ENGLAND: Championship",
      "oraStart": "17:00",
      "timestampStart": 1764428400,
      "oraVerificare": "17:45",
      "timestampVerificare": 1764431100,
      "minutMeci": 45,
      "status": "completat",
      "completedAt": "2025-11-29T15:44:55.471Z",
      "statsFile": "stats-MFbGD3e4-HT.json"
    },
    {
      "matchId": "IshPBsQG",
      "homeTeam": "Norwich",
      "awayTeam": "QPR",
      "liga": "ENGLAND: Championship",
      "oraStart": "17:00",
      "timestampStart": 1764428400,
      "oraVerificare": "17:45",
      "timestampVerificare": 1764431100,
      "minutMeci": 45,
      "status": "completat",
      "completedAt": "2025-11-29T15:44:57.428Z",
      "statsFile": "stats-IshPBsQG-HT.json"
    },
    {
      "matchId": "MTwkS2Ac",
      "homeTeam": "Sheffield Wed",
      "awayTeam": "Preston",
      "liga": "ENGLAND: Championship",
      "oraStart": "17:00",
      "timestampStart": 1764428400,
      "oraVerificare": "17:45",
      "timestampVerificare": 1764431100,
      "minutMeci": 45,
      "status": "completat",
      "completedAt": "2025-11-29T15:44:59.760Z",
      "statsFile": "stats-MTwkS2Ac-HT.json"
    },
    {
      "matchId": "YJuM6xW6",
      "homeTeam": "Wrexham",
      "awayTeam": "Blackburn",
      "liga": "ENGLAND: Championship",
      "oraStart": "17:00",
      "timestampStart": 1764428400,
      "oraVerificare": "17:45",
      "timestampVerificare": 1764431100,
      "minutMeci": 45,
      "status": "completat",
      "completedAt": "2025-11-29T15:45:00.212Z",
      "statsFile": "stats-YJuM6xW6-HT.json"
    },
    {
      "matchId": "jNCvFO9C",
      "homeTeam": "Dundee FC",
      "awayTeam": "St. Mirren",
      "liga": "SCOTLAND: Premiership",
      "oraStart": "17:00",
      "timestampStart": 1764428400,
      "oraVerificare": "17:45",
      "timestampVerificare": 1764431100,
      "minutMeci": 45,
      "status": "completat",
      "completedAt": "2025-11-29T15:45:02.247Z",
      "statsFile": "stats-jNCvFO9C-HT.json"
    },
    {
      "matchId": "nDKBDWk5",
      "homeTeam": "Motherwell",
      "awayTeam": "Hearts",
      "liga": "SCOTLAND: Premiership",
      "oraStart": "17:00",
      "timestampStart": 1764428400,
      "oraVerificare": "17:45",
      "timestampVerificare": 1764431100,
      "minutMeci": 45,
      "status": "completat",
      "completedAt": "2025-11-29T15:45:02.662Z",
      "statsFile": "stats-nDKBDWk5-HT.json"
    },
    {
      "matchId": "06PbPm5d",
      "homeTeam": "Barcelona",
      "awayTeam": "Alaves",
      "liga": "SPAIN: LaLiga",
      "oraStart": "17:15",
      "timestampStart": 1764429300,
      "oraVerificare": "18:00",
      "timestampVerificare": 1764432000,
      "minutMeci": 45,
      "status": "completat",
      "completedAt": "2025-11-29T15:59:31.907Z",
      "statsFile": "stats-06PbPm5d-HT.json"
    },
    {
      "matchId": "tSuKbSHb",
      "homeTeam": "Cultural Leonesa",
      "awayTeam": "Granada CF",
      "liga": "SPAIN: LaLiga2",
      "oraStart": "17:15",
      "timestampStart": 1764429300,
      "oraVerificare": "18:00",
      "timestampVerificare": 1764432000,
      "minutMeci": 45,
      "status": "completat",
      "completedAt": "2025-11-29T15:59:32.380Z",
      "statsFile": "stats-tSuKbSHb-HT.json"
    },
    {
      "matchId": "Qauq9TJM",
      "homeTeam": "OFI Crete",
      "awayTeam": "Volos",
      "liga": "GREECE: Super League",
      "oraStart": "17:30",
      "timestampStart": 1764430200,
      "oraVerificare": "18:15",
      "timestampVerificare": 1764432900,
      "minutMeci": 45,
      "status": "completat",
      "completedAt": "2025-11-29T16:14:39.838Z",
      "statsFile": "stats-Qauq9TJM-HT.json"
    },
    {
      "matchId": "pCSrxh66",
      "homeTeam": "Casa Pia",
      "awayTeam": "Alverca",
      "liga": "PORTUGAL: Liga Portugal",
      "oraStart": "17:30",
      "timestampStart": 1764430200,
      "oraVerificare": "18:15",
      "timestampVerificare": 1764432900,
      "minutMeci": 45,
      "status": "completat",
      "completedAt": "2025-11-29T16:14:40.326Z",
      "statsFile": "stats-pCSrxh66-HT.json"
    },
    {
      "matchId": "6RGizWzJ",
      "homeTeam": "Moreirense",
      "awayTeam": "Famalicao",
      "liga": "PORTUGAL: Liga Portugal",
      "oraStart": "17:30",
      "timestampStart": 1764430200,
      "oraVerificare": "18:15",
      "timestampVerificare": 1764432900,
      "minutMeci": 45,
      "status": "completat",
      "completedAt": "2025-11-29T16:14:45.109Z",
      "statsFile": "stats-6RGizWzJ-HT.json"
    },
    {
      "matchId": "z5uwKxK5",
      "homeTeam": "Vojvodina",
      "awayTeam": "Sp. Subotica",
      "liga": "SERBIA: Mozzart Bet Super Liga",
      "oraStart": "17:30",
      "timestampStart": 1764430200,
      "oraVerificare": "18:15",
      "timestampVerificare": 1764432900,
      "minutMeci": 45,
      "status": "completat",
      "completedAt": "2025-11-29T16:14:51.551Z",
      "statsFile": "stats-z5uwKxK5-HT.json"
    },
    {
      "matchId": "CnppXE0K",
      "homeTeam": "Austria Vienna",
      "awayTeam": "Tirol",
      "liga": "AUSTRIA: Bundesliga",
      "oraStart": "18:00",
      "timestampStart": 1764432000,
      "oraVerificare": "18:45",
      "timestampVerificare": 1764434700,
      "minutMeci": 45,
      "status": "completat",
      "completedAt": "2025-11-29T16:44:40.990Z",
      "statsFile": "stats-CnppXE0K-HT.json"
    },
    {
      "matchId": "4pPOPWhf",
      "homeTeam": "Grazer AK",
      "awayTeam": "BW Linz",
      "liga": "AUSTRIA: Bundesliga",
      "oraStart": "18:00",
      "timestampStart": 1764432000,
      "oraVerificare": "18:45",
      "timestampVerificare": 1764434700,
      "minutMeci": 45,
      "status": "completat",
      "completedAt": "2025-11-29T16:44:41.455Z",
      "statsFile": "stats-4pPOPWhf-HT.json"
    },
    {
      "matchId": "n9hb9B8D",
      "homeTeam": "Ried",
      "awayTeam": "Wolfsberger AC",
      "liga": "AUSTRIA: Bundesliga",
      "oraStart": "18:00",
      "timestampStart": 1764432000,
      "oraVerificare": "18:45",
      "timestampVerificare": 1764434700,
      "minutMeci": 45,
      "status": "completat",
      "completedAt": "2025-11-29T16:44:43.411Z",
      "statsFile": "stats-n9hb9B8D-HT.json"
    },
    {
      "matchId": "p6F1M1tP",
      "homeTeam": "Monaco",
      "awayTeam": "PSG",
      "liga": "FRANCE: Ligue 1",
      "oraStart": "18:00",
      "timestampStart": 1764432000,
      "oraVerificare": "18:45",
      "timestampVerificare": 1764434700,
      "minutMeci": 45,
      "status": "completat",
      "completedAt": "2025-11-29T16:44:50.143Z",
      "statsFile": "stats-p6F1M1tP-HT.json"
    },
    {
      "matchId": "zq427az0",
      "homeTeam": "Novi Pazar",
      "awayTeam": "Napredak",
      "liga": "SERBIA: Mozzart Bet Super Liga",
      "oraStart": "18:00",
      "timestampStart": 1764432000,
      "oraVerificare": "18:45",
      "timestampVerificare": 1764434700,
      "minutMeci": 45,
      "status": "completat",
      "completedAt": "2025-11-29T16:44:50.646Z",
      "statsFile": "stats-zq427az0-HT.json"
    },
    {
      "matchId": "nFgmtiW8",
      "homeTeam": "Korona Kielce",
      "awayTeam": "Cracovia",
      "liga": "POLAND: Ekstraklasa",
      "oraStart": "18:30",
      "timestampStart": 1764433800,
      "oraVerificare": "19:15",
      "timestampVerificare": 1764436500,
      "minutMeci": 45,
      "status": "completat",
      "completedAt": "2025-11-29T17:14:49.485Z",
      "statsFile": "stats-nFgmtiW8-HT.json"
    },
    {
      "matchId": "lWJU5xwK",
      "homeTeam": "Juventus",
      "awayTeam": "Cagliari",
      "liga": "ITALY: Serie A",
      "oraStart": "19:00",
      "timestampStart": 1764435600,
      "oraVerificare": "19:45",
      "timestampVerificare": 1764438300,
      "minutMeci": 45,
      "status": "completat",
      "completedAt": "2025-11-29T17:44:43.247Z",
      "statsFile": "stats-lWJU5xwK-HT.json"
    },
    {
      "matchId": "YagsElTP",
      "homeTeam": "Lugano",
      "awayTeam": "Sion",
      "liga": "SWITZERLAND: Super League",
      "oraStart": "19:00",
      "timestampStart": 1764435600,
      "oraVerificare": "19:45",
      "timestampVerificare": 1764438300,
      "minutMeci": 45,
      "status": "completat",
      "completedAt": "2025-11-29T17:44:51.585Z",
      "statsFile": "stats-YagsElTP-HT.json"
    },
    {
      "matchId": "KdRU4pjC",
      "homeTeam": "Zurich",
      "awayTeam": "Grasshoppers",
      "liga": "SWITZERLAND: Super League",
      "oraStart": "19:00",
      "timestampStart": 1764435600,
      "oraVerificare": "19:45",
      "timestampVerificare": 1764438300,
      "minutMeci": 45,
      "status": "completat",
      "completedAt": "2025-11-29T17:44:54.316Z",
      "statsFile": "stats-KdRU4pjC-HT.json"
    },
    {
      "matchId": "GAJUISeJ",
      "homeTeam": "Kasimpasa",
      "awayTeam": "Basaksehir",
      "liga": "TURKEY: Super Lig",
      "oraStart": "19:00",
      "timestampStart": 1764435600,
      "oraVerificare": "19:45",
      "timestampVerificare": 1764438300,
      "minutMeci": 45,
      "status": "completat",
      "completedAt": "2025-11-29T17:45:00.631Z",
      "statsFile": "stats-GAJUISeJ-HT.json"
    },
    {
      "matchId": "thmmyABm",
      "homeTeam": "Trabzonspor",
      "awayTeam": "Konyaspor",
      "liga": "TURKEY: Super Lig",
      "oraStart": "19:00",
      "timestampStart": 1764435600,
      "oraVerificare": "19:45",
      "timestampVerificare": 1764438300,
      "minutMeci": 45,
      "status": "completat",
      "completedAt": "2025-11-29T17:45:01.095Z",
      "statsFile": "stats-thmmyABm-HT.json"
    },
    {
      "matchId": "vDfF6wDc",
      "homeTeam": "Everton",
      "awayTeam": "Newcastle",
      "liga": "ENGLAND: Premier League",
      "oraStart": "19:30",
      "timestampStart": 1764437400,
      "oraVerificare": "20:15",
      "timestampVerificare": 1764440100,
      "minutMeci": 45,
      "status": "completat",
      "completedAt": "2025-11-29T18:14:44.394Z",
      "statsFile": "stats-vDfF6wDc-HT.json"
    },
    {
      "matchId": "GILJXTHr",
      "homeTeam": "Bayer Leverkusen",
      "awayTeam": "Dortmund",
      "liga": "GERMANY: Bundesliga",
      "oraStart": "19:30",
      "timestampStart": 1764437400,
      "oraVerificare": "20:15",
      "timestampVerificare": 1764440100,
      "minutMeci": 45,
      "status": "completat",
      "completedAt": "2025-11-29T18:14:46.331Z",
      "statsFile": "stats-GILJXTHr-HT.json"
    },
    {
      "matchId": "nghHfU4T",
      "homeTeam": "Aris",
      "awayTeam": "AEL Larissa",
      "liga": "GREECE: Super League",
      "oraStart": "19:30",
      "timestampStart": 1764437400,
      "oraVerificare": "20:15",
      "timestampVerificare": 1764440100,
      "minutMeci": 45,
      "status": "completat",
      "completedAt": "2025-11-29T18:14:48.251Z",
      "statsFile": "stats-nghHfU4T-HT.json"
    },
    {
      "matchId": "YqRZCBKc",
      "homeTeam": "Kifisia",
      "awayTeam": "Panserraikos",
      "liga": "GREECE: Super League",
      "oraStart": "19:30",
      "timestampStart": 1764437400,
      "oraVerificare": "20:15",
      "timestampVerificare": 1764440100,
      "minutMeci": 45,
      "status": "completat",
      "completedAt": "2025-11-29T18:14:48.795Z",
      "statsFile": "stats-YqRZCBKc-HT.json"
    },
    {
      "matchId": "A1KNEsrQ",
      "homeTeam": "Partizan",
      "awayTeam": "Javor",
      "liga": "SERBIA: Mozzart Bet Super Liga",
      "oraStart": "19:30",
      "timestampStart": 1764437400,
      "oraVerificare": "20:15",
      "timestampVerificare": 1764440100,
      "minutMeci": 45,
      "status": "completat",
      "completedAt": "2025-11-29T18:14:58.092Z",
      "statsFile": "stats-A1KNEsrQ-HT.json"
    },
    {
      "matchId": "hlrKT7IO",
      "homeTeam": "Albacete",
      "awayTeam": "Dep. La Coruna",
      "liga": "SPAIN: LaLiga2",
      "oraStart": "19:30",
      "timestampStart": 1764437400,
      "oraVerificare": "20:15",
      "timestampVerificare": 1764440100,
      "minutMeci": 45,
      "status": "completat",
      "completedAt": "2025-11-29T18:15:05.351Z",
      "statsFile": "stats-hlrKT7IO-HT.json"
    },
    {
      "matchId": "vuHxnkYh",
      "homeTeam": "Almeria",
      "awayTeam": "Huesca",
      "liga": "SPAIN: LaLiga2",
      "oraStart": "19:30",
      "timestampStart": 1764437400,
      "oraVerificare": "20:15",
      "timestampVerificare": 1764440100,
      "minutMeci": 45,
      "status": "completat",
      "completedAt": "2025-11-29T18:15:07.175Z",
      "statsFile": "stats-vuHxnkYh-HT.json"
    },
    {
      "matchId": "llgIzRPF",
      "homeTeam": "Sittard",
      "awayTeam": "Heracles",
      "liga": "NETHERLANDS: Eredivisie",
      "oraStart": "19:45",
      "timestampStart": 1764438300,
      "oraVerificare": "20:30",
      "timestampVerificare": 1764441000,
      "minutMeci": 45,
      "status": "completat",
      "completedAt": "2025-11-29T18:29:44.949Z",
      "statsFile": "stats-llgIzRPF-HT.json"
    },
    {
      "matchId": "4USfHEjt",
      "homeTeam": "Kilmarnock",
      "awayTeam": "Dundee Utd",
      "liga": "SCOTLAND: Premiership",
      "oraStart": "19:45",
      "timestampStart": 1764438300,
      "oraVerificare": "20:30",
      "timestampVerificare": 1764441000,
      "minutMeci": 45,
      "status": "completat",
      "completedAt": "2025-11-29T18:29:45.394Z",
      "statsFile": "stats-4USfHEjt-HT.json"
    },
    {
      "matchId": "2NcBBpS6",
      "homeTeam": "Paris FC",
      "awayTeam": "Auxerre",
      "liga": "FRANCE: Ligue 1",
      "oraStart": "20:00",
      "timestampStart": 1764439200,
      "oraVerificare": "20:45",
      "timestampVerificare": 1764441900,
      "minutMeci": 45,
      "status": "completat",
      "completedAt": "2025-11-29T18:44:45.581Z",
      "statsFile": "stats-2NcBBpS6-HT.json"
    },
    {
      "matchId": "IJa9hDjm",
      "homeTeam": "Nacional",
      "awayTeam": "Benfica",
      "liga": "PORTUGAL: Liga Portugal",
      "oraStart": "20:00",
      "timestampStart": 1764439200,
      "oraVerificare": "20:45",
      "timestampVerificare": 1764441900,
      "minutMeci": 45,
      "status": "completat",
      "completedAt": "2025-11-29T18:44:53.477Z",
      "statsFile": "stats-IJa9hDjm-HT.json"
    },
    {
      "matchId": "8ARqXF1C",
      "homeTeam": "K. Lierse S.K.",
      "awayTeam": "Anderlecht U23",
      "liga": "BELGIUM: Challenger Pro League",
      "oraStart": "21:00",
      "timestampStart": 1764442800,
      "oraVerificare": "21:45",
      "timestampVerificare": 1764445500,
      "minutMeci": 45,
      "status": "completat",
      "completedAt": "2025-11-29T19:44:48.091Z",
      "statsFile": "stats-8ARqXF1C-HT.json"
    },
    {
      "matchId": "GfgZsXFU",
      "homeTeam": "Patro Eisden",
      "awayTeam": "Gent U23",
      "liga": "BELGIUM: Challenger Pro League",
      "oraStart": "21:00",
      "timestampStart": 1764442800,
      "oraVerificare": "21:45",
      "timestampVerificare": 1764445500,
      "minutMeci": 45,
      "status": "completat",
      "completedAt": "2025-11-29T19:44:56.442Z",
      "statsFile": "stats-GfgZsXFU-HT.json"
    },
    {
      "matchId": "8UsdvV0L",
      "homeTeam": "GKS Katowice",
      "awayTeam": "Pogon Szczecin",
      "liga": "POLAND: Ekstraklasa",
      "oraStart": "21:15",
      "timestampStart": 1764443700,
      "oraVerificare": "22:00",
      "timestampVerificare": 1764446400,
      "minutMeci": 45,
      "status": "completat",
      "completedAt": "2025-11-29T19:59:56.165Z",
      "statsFile": "stats-8UsdvV0L-HT.json"
    },
    {
      "matchId": "ldHhWOUN",
      "homeTeam": "Magdeburg",
      "awayTeam": "Nurnberg",
      "liga": "GERMANY: 2. Bundesliga",
      "oraStart": "21:30",
      "timestampStart": 1764444600,
      "oraVerificare": "22:15",
      "timestampVerificare": 1764447300,
      "minutMeci": 45,
      "status": "completat",
      "completedAt": "2025-11-29T20:14:56.826Z",
      "statsFile": "stats-ldHhWOUN-HT.json"
    },
    {
      "matchId": "jHZD8Sjm",
      "homeTeam": "Luzern",
      "awayTeam": "Winterthur",
      "liga": "SWITZERLAND: Super League",
      "oraStart": "21:30",
      "timestampStart": 1764444600,
      "oraVerificare": "22:15",
      "timestampVerificare": 1764447300,
      "minutMeci": 45,
      "status": "completat",
      "completedAt": "2025-11-29T20:14:57.316Z",
      "statsFile": "stats-jHZD8Sjm-HT.json"
    },
    {
      "matchId": "AgluwlE8",
      "homeTeam": "Charleroi",
      "awayTeam": "RAAL La Louviere",
      "liga": "BELGIUM: Jupiler Pro League",
      "oraStart": "21:45",
      "timestampStart": 1764445500,
      "oraVerificare": "22:30",
      "timestampVerificare": 1764448200,
      "minutMeci": 45,
      "status": "completat",
      "completedAt": "2025-11-29T20:29:56.745Z",
      "statsFile": "stats-AgluwlE8-HT.json"
    },
    {
      "matchId": "ED39bfVg",
      "homeTeam": "AC Milan",
      "awayTeam": "Lazio",
      "liga": "ITALY: Serie A",
      "oraStart": "21:45",
      "timestampStart": 1764445500,
      "oraVerificare": "22:30",
      "timestampVerificare": 1764448200,
      "minutMeci": 45,
      "status": "completat",
      "completedAt": "2025-11-29T20:30:03.989Z",
      "statsFile": "stats-ED39bfVg-HT.json"
    },
    {
      "matchId": "YZVAeD4d",
      "homeTeam": "Tottenham",
      "awayTeam": "Fulham",
      "liga": "ENGLAND: Premier League",
      "oraStart": "22:00",
      "timestampStart": 1764446400,
      "oraVerificare": "22:45",
      "timestampVerificare": 1764449100,
      "minutMeci": 45,
      "status": "completat",
      "completedAt": "2025-11-29T20:44:49.948Z",
      "statsFile": "stats-YZVAeD4d-HT.json"
    },
    {
      "matchId": "0SCNEq3d",
      "homeTeam": "Nijmegen",
      "awayTeam": "Sparta Rotterdam",
      "liga": "NETHERLANDS: Eredivisie",
      "oraStart": "22:00",
      "timestampStart": 1764446400,
      "oraVerificare": "22:45",
      "timestampVerificare": 1764449100,
      "minutMeci": 45,
      "status": "completat",
      "completedAt": "2025-11-29T20:44:57.589Z",
      "statsFile": "stats-0SCNEq3d-HT.json"
    },
    {
      "matchId": "YwUqVIyI",
      "homeTeam": "Atl. Madrid",
      "awayTeam": "Oviedo",
      "liga": "SPAIN: LaLiga",
      "oraStart": "22:00",
      "timestampStart": 1764446400,
      "oraVerificare": "22:45",
      "timestampVerificare": 1764449100,
      "minutMeci": 45,
      "status": "completat",
      "completedAt": "2025-11-29T20:44:57.988Z",
      "statsFile": "stats-YwUqVIyI-HT.json"
    },
    {
      "matchId": "8vXzepHN",
      "homeTeam": "Valladolid",
      "awayTeam": "Malaga",
      "liga": "SPAIN: LaLiga2",
      "oraStart": "22:00",
      "timestampStart": 1764446400,
      "oraVerificare": "22:45",
      "timestampVerificare": 1764449100,
      "minutMeci": 45,
      "status": "completat",
      "completedAt": "2025-11-29T20:44:58.393Z",
      "statsFile": "stats-8vXzepHN-HT.json"
    },
    {
      "matchId": "QaX9QDht",
      "homeTeam": "Marseille",
      "awayTeam": "Toulouse",
      "liga": "FRANCE: Ligue 1",
      "oraStart": "22:05",
      "timestampStart": 1764446700,
      "oraVerificare": "22:50",
      "timestampVerificare": 1764449400,
      "minutMeci": 45,
      "status": "completat",
      "completedAt": "2025-11-29T20:49:50.132Z",
      "statsFile": "stats-QaX9QDht-HT.json"
    },
    {
      "matchId": "W829NhiD",
      "homeTeam": "Gil Vicente",
      "awayTeam": "Tondela",
      "liga": "PORTUGAL: Liga Portugal",
      "oraStart": "22:30",
      "timestampStart": 1764448200,
      "oraVerificare": "23:15",
      "timestampVerificare": 1764450900,
      "minutMeci": 45,
      "status": "completat",
      "completedAt": "2025-11-29T21:15:00.816Z",
      "statsFile": "stats-W829NhiD-HT.json"
    },
    {
      "matchId": "IwUrkvRk",
      "homeTeam": "Palmeiras (Bra)",
      "awayTeam": "Flamengo RJ (Bra)",
      "liga": "SOUTH AMERICA: Copa Libertadores - Play Offs",
      "oraStart": "23:00",
      "timestampStart": 1764450000,
      "oraVerificare": "23:45",
      "timestampVerificare": 1764452700,
      "minutMeci": 45,
      "status": "completat",
      "completedAt": "2025-11-29T21:44:52.418Z",
      "statsFile": "stats-IwUrkvRk-HT.json"
    }
  ]
}